craftaxlm/classic.py
craftaxlm/craftax.py
craftaxlm/src/__init__.py
craftaxlm/src/classic.py
craftaxlm/src/craftax.py
craftaxlm/src/shared.py
craftaxlm-0.1.0.dist-info/LICENSE
craftaxlm-0.1.0.dist-info/METADATA
craftaxlm-0.1.0.dist-info/WHEEL
craftaxlm-0.1.0.dist-info/RECORD
