Metadata-Version: 2.1
Name: craftaxlm
Version: 0.1.0
Summary: 
Author: Josh Purtell
Author-email: jmvpurtell@gmail.com
Requires-Python: >=3.11,<4.0
Classifier: Programming Language :: Python :: 3
Classifier: Programming Language :: Python :: 3.11
Classifier: Programming Language :: Python :: 3.12
Requires-Dist: craftax (>=1.4.3,<2.0.0)
Requires-Dist: jax (>=0.4.30,<0.5.0)
